tagmanager/__init__.py
tagmanager/cli.py
tagmanager/config.ini
tagmanager/configReader.py
tagmanager/config_manager.py
tagmanager/app/__init__.py
tagmanager/app/helpers.py
tagmanager/app/add/__init__.py
tagmanager/app/add/handler.py
tagmanager/app/add/service.py
tagmanager/app/bulk/__init__.py
tagmanager/app/bulk/handler.py
tagmanager/app/bulk/service.py
tagmanager/app/config/__init__.py
tagmanager/app/config/handler.py
tagmanager/app/config/service.py
tagmanager/app/filter/__init__.py
tagmanager/app/filter/handler.py
tagmanager/app/filter/service.py
tagmanager/app/list_all/__init__.py
tagmanager/app/list_all/handler.py
tagmanager/app/list_all/service.py
tagmanager/app/paths/__init__.py
tagmanager/app/paths/handler.py
tagmanager/app/paths/service.py
tagmanager/app/remove/__init__.py
tagmanager/app/remove/handler.py
tagmanager/app/remove/service.py
tagmanager/app/search/__init__.py
tagmanager/app/search/handler.py
tagmanager/app/search/service.py
tagmanager/app/stats/__init__.py
tagmanager/app/stats/handler.py
tagmanager/app/stats/service.py
tagmanager/app/storage/__init__.py
tagmanager/app/storage/handler.py
tagmanager/app/storage/service.py
tagmanager/app/tags/__init__.py
tagmanager/app/tags/handler.py
tagmanager/app/tags/service.py
tagmanager/app/visualization/__init__.py
tagmanager/app/visualization/handler.py
tagmanager/app/visualization/service.py
tagmanager_cli-1.3.3.dist-info/licenses/LICENSE
tagmanager_cli-1.3.3.dist-info/METADATA
tagmanager_cli-1.3.3.dist-info/WHEEL
tagmanager_cli-1.3.3.dist-info/entry_points.txt
tagmanager_cli-1.3.3.dist-info/top_level.txt
tagmanager_cli-1.3.3.dist-info/RECORD
