Metadata-Version: 2.4
Name: tagmanager-cli
Version: 1.3.3
Summary: The Ultimate Command-Line File Tagging System - Transform chaos into order with intelligent file organization
Author-email: David Chincharashvili <david@example.com>
Maintainer-email: David Chincharashvili <david@example.com>
License: MIT
Project-URL: Homepage, https://github.com/davidtbilisi/TagManager
Project-URL: Documentation, https://github.com/davidtbilisi/TagManager#readme
Project-URL: Repository, https://github.com/davidtbilisi/TagManager.git
Project-URL: Bug Tracker, https://github.com/davidtbilisi/TagManager/issues
Project-URL: Changelog, https://github.com/davidtbilisi/TagManager/releases
Keywords: file-management,tagging,organization,cli,productivity,file-system,search,metadata
Classifier: Development Status :: 5 - Production/Stable
Classifier: Environment :: Console
Classifier: Intended Audience :: Developers
Classifier: Intended Audience :: End Users/Desktop
Classifier: Intended Audience :: System Administrators
Classifier: License :: OSI Approved :: MIT License
Classifier: Operating System :: OS Independent
Classifier: Programming Language :: Python :: 3
Classifier: Programming Language :: Python :: 3.7
Classifier: Programming Language :: Python :: 3.8
Classifier: Programming Language :: Python :: 3.9
Classifier: Programming Language :: Python :: 3.10
Classifier: Programming Language :: Python :: 3.11
Classifier: Programming Language :: Python :: 3.12
Classifier: Topic :: System :: Filesystems
Classifier: Topic :: Utilities
Classifier: Topic :: System :: Systems Administration
Classifier: Topic :: Software Development :: Libraries :: Python Modules
Requires-Python: >=3.7
License-File: LICENSE
Requires-Dist: typer>=0.9.0
Requires-Dist: rich>=10.0.0
Provides-Extra: test
Requires-Dist: pytest>=7.0.0; extra == "test"
Requires-Dist: pytest-cov>=4.0.0; extra == "test"
Provides-Extra: dev
Requires-Dist: pytest>=7.0.0; extra == "dev"
Requires-Dist: pytest-cov>=4.0.0; extra == "dev"
Requires-Dist: black>=22.0.0; extra == "dev"
Requires-Dist: flake8>=5.0.0; extra == "dev"
Dynamic: license-file
